magic_scrape-0.1.2.dist-info/METADATA
magic_scrape-0.1.2.dist-info/WHEEL
magic_scrape-0.1.2.dist-info/entry_points.txt
magic_scrape/__init__.py
magic_scrape/cli.py
magic_scrape/config.py
magic_scrape/log.py
magic_scrape/scrape.py
magic_scrape-0.1.2.dist-info/RECORD
